yamlinclude/__init__.py
yamlinclude/main.py
yaml_include-1.0.0.dist-info/METADATA
yaml_include-1.0.0.dist-info/WHEEL
yaml_include-1.0.0.dist-info/entry_points.txt
yaml_include-1.0.0.dist-info/top_level.txt
yaml_include-1.0.0.dist-info/RECORD
