Metadata-Version: 2.1
Name: yaml-include
Version: 1.0.0
Summary: Tool to generate yaml file with include
Home-page: UNKNOWN
Author: Mahe Thomas
Author-email: thomas.mahe@nxp.com
License: UNKNOWN
Platform: UNKNOWN
Classifier: Programming Language :: Python :: 3
Classifier: License :: OSI Approved :: MIT License
Classifier: Operating System :: OS Independent
Requires-Python: >=3.4
